t2g_sdk/__init__.py
t2g_sdk/client.py
t2g_sdk/config.py
t2g_sdk/exceptions.py
t2g_sdk/models.py
t2g_sdk/services/__init__.py
t2g_sdk/services/base_service.py
t2g_sdk/services/file_service.py
t2g_sdk/services/job_service.py
t2g_sdk/services/neo4j_service.py
t2g_sdk/services/ontology_service.py
t2g_sdk-1.0.0rc15.dist-info/METADATA
t2g_sdk-1.0.0rc15.dist-info/WHEEL
t2g_sdk-1.0.0rc15.dist-info/RECORD
